{"activity":{"id":"6009647839384c001eed9809","createdAt":"2021-01-21T11:24:40.814Z","updatedAt":"2021-01-27T07:00:28.151Z","deleted":false,"name":"Exercise 4","description":"Calculations with surds","courseId":"6009612f39384c001eed3400","code":"QK9DI","orderNumber":1,"type":"EXERCISE","parentId":"6009647839384c001eed9807"},"problems":[{"id":"6009647939384c001eed980b","createdAt":"2021-01-21T11:24:41.2Z","updatedAt":"2021-01-28T11:24:41.541Z","deleted":false,"orderNumber":1,"folderId":"6009647839384c001eed9809","courseId":"6009612f39384c001eed3400","siyavulaNumber":"1","code":"OWBGS","problem":{"en":{"latex":"Determine between which two consecutive integers the following lie, without using a calculator:","html":"Determine between which two consecutive integers the following lie, without using a calculator:"},"af":{"latex":"Bepaal tussen watter twee opeenvolgende telgetalle die volgende getalle lê, sonder om 'n sakrekenaar te gebruik:","html":"Bepaal tussen watter twee opeenvolgende telgetalle die volgende getalle lê, sonder om 'n sakrekenaar te gebruik:"}},"memo":{"en":{"latex":" ","html":" "},"af":{"latex":"% Empty","html":"% Empty"}},"type":"multiple-choice"},{"id":"6009648839384c001eed985d","createdAt":"2021-01-21T11:24:56.702Z","updatedAt":"2022-01-21T18:11:07.602Z","deleted":false,"orderNumber":2,"folderId":"6009647839384c001eed9809","courseId":"6009612f39384c001eed3400","siyavulaNumber":"1","code":"17Y1T","problem":{"en":{"latex":"Estimate the following surds to the nearest \\( 1 \\) decimal place, without using a calculator.","html":"Estimate the following surds to the nearest \\( 1 \\) decimal place, without using a calculator."},"af":{"latex":"Bereken die volgende wortelvorme tot die naaste \\( 1 \\) desimale plek, sonder om 'n sakrekenaar te gebruik.","html":"Bereken die volgende wortelvorme tot die naaste \\( 1 \\) desimale plek, sonder om 'n sakrekenaar te gebruik."}},"memo":{"en":{"latex":" ","html":" "},"af":{"latex":"% Empty","html":"% Empty"}},"type":"multiple-choice"},{"id":"6009648f39384c001eed987f","createdAt":"2021-01-21T11:25:03.037Z","updatedAt":"2021-01-21T11:25:03.037Z","deleted":false,"orderNumber":3,"folderId":"6009647839384c001eed9809","courseId":"6009612f39384c001eed3400","siyavulaNumber":"1","code":"2NKNM","problem":{"en":{"latex":"Consider the following list of numbers:<br> \\( \\frac{27}{7} \\ ; \\ \\sqrt{19} \\ ; \\ 2\\pi \\ ; \\ 0,45 \\ ; \\ \\text{0,}\\overline{45} \\ ; \\ -\\sqrt{\\frac{9}{4}} \\ ; \\ 6 \\ ; \\ -\\sqrt{8} \\ ; \\ \\sqrt{51} \\)<br>Without using a calculator, rank all the numbers in ascending order.","html":"Consider the following list of numbers:<br> \\( \\frac{27}{7} \\ ; \\ \\sqrt{19} \\ ; \\ 2\\pi \\ ; \\ 0,45 \\ ; \\ \\text{0,}\\overline{45} \\ ; \\ -\\sqrt{\\frac{9}{4}} \\ ; \\ 6 \\ ; \\ -\\sqrt{8} \\ ; \\ \\sqrt{51} \\)<br>Without using a calculator, rank all the numbers in ascending order."},"af":{"latex":"Beskou die volgende lys van getalle:<br> \\( \\frac{27}{7} \\ ; \\ \\sqrt{19} \\ ; \\ 2\\pi \\ ; \\ 0,45 \\ ; \\ \\text{0,}\\overline{45} \\ ; \\ -\\sqrt{\\frac{9}{4}} \\ ; \\ 6 \\ ; \\ -\\sqrt{8} \\ ; \\ \\sqrt{51} \\)<br>Sonder om 'n sakrekenaar te gebruik, rangskik al die getalle in stygende volgorde.","html":"Beskou die volgende lys van getalle:<br> \\( \\frac{27}{7} \\ ; \\ \\sqrt{19} \\ ; \\ 2\\pi \\ ; \\ 0,45 \\ ; \\ \\text{0,}\\overline{45} \\ ; \\ -\\sqrt{\\frac{9}{4}} \\ ; \\ 6 \\ ; \\ -\\sqrt{8} \\ ; \\ \\sqrt{51} \\)<br>Sonder om 'n sakrekenaar te gebruik, rangskik al die getalle in stygende volgorde."}},"memo":{"en":{"latex":"Remember that negative numbers are smaller than positive numbers. It may also be helpful to write the fractions as decimals to help you estimate the number. For the surds you can estimate between which two numbers the surd lies and use that to help you rank these numbers.<br>1. \\( \\frac{27}{7} \\approx 3,857 \\)<br>2. \\( \\sqrt{19} \\)<br>3. \\( 2\\pi \\approx 6,28 \\)<br>4. \\( -\\sqrt{\\frac{9}{4}} = -\\frac{3}{2} = -\\text{1,5} \\)<br>5. \\( -\\sqrt{8} \\) lies between \\( -2 \\) and \\( -3 \\)<br>6. \\( \\sqrt{51} \\) lies between \\( 7 \\) and \\( 8 \\)<br>Also note that \\( 0,45 < 0\\overline{45} \\)<br>There we get the following:<br> \\( -\\sqrt{8} \\ ; \\ -\\sqrt{\\frac{9}{4}} \\ ; \\ \\text{0,45} \\ ; \\ \\text{0,}\\overline{45} \\ ; \\ \\frac{27}{7} \\ ; \\ \\sqrt{19} \\ ; \\ 6 \\ ; \\ 2\\pi \\ ; \\ \\sqrt{51} \\)","html":"Remember that negative numbers are smaller than positive numbers. It may also be helpful to write the fractions as decimals to help you estimate the number. For the surds you can estimate between which two numbers the surd lies and use that to help you rank these numbers.<br>1. \\( \\frac{27}{7} \\approx 3,857 \\)<br>2. \\( \\sqrt{19} \\)<br>3. \\( 2\\pi \\approx 6,28 \\)<br>4. \\( -\\sqrt{\\frac{9}{4}} = -\\frac{3}{2} = -\\text{1,5} \\)<br>5. \\( -\\sqrt{8} \\) lies between \\( -2 \\) and \\( -3 \\)<br>6. \\( \\sqrt{51} \\) lies between \\( 7 \\) and \\( 8 \\)<br>Also note that \\( 0,45 < 0\\overline{45} \\)<br>There we get the following:<br> \\( -\\sqrt{8} \\ ; \\ -\\sqrt{\\frac{9}{4}} \\ ; \\ \\text{0,45} \\ ; \\ \\text{0,}\\overline{45} \\ ; \\ \\frac{27}{7} \\ ; \\ \\sqrt{19} \\ ; \\ 6 \\ ; \\ 2\\pi \\ ; \\ \\sqrt{51} \\)"},"af":{"latex":"Onthou dat negatiewe getalle kleiner as positiewe getalle is. Dit kan help om die breuke as desimale neer te skryf om jou te help om die getal te bereken. Vir die wortelvorms kan jy bereken tussen watter twee getalle die wortelvorm lê en dit gebruik om jou te help om die getalle te rangskik.<br>1. \\( \\frac{27}{7} \\approx 3,857 \\)<br>2. \\( \\sqrt{19} \\)<br>3. \\( 2\\pi \\approx 6,28 \\)<br>4. \\( -\\sqrt{\\frac{9}{4}} = -\\frac{3}{2} = -\\text{1,5} \\)<br>5. \\( -\\sqrt{8} \\) lê tussen \\( -2 \\) en \\( -3 \\)<br>6. \\( \\sqrt{51} \\) lê tussen \\( 7 \\) en \\( 8 \\)<br>Merk ook op dat \\( 0,45 < 0\\overline{45} \\)<br>Dan kry ons die volgende:<br> \\( -\\sqrt{8} \\ ; \\ -\\sqrt{\\frac{9}{4}} \\ ; \\ \\text{0,45} \\ ; \\ \\text{0,}\\overline{45} \\ ; \\ \\frac{27}{7} \\ ; \\ \\sqrt{19} \\ ; \\ 6 \\ ; \\ 2\\pi \\ ; \\ \\sqrt{51} \\)","html":"Onthou dat negatiewe getalle kleiner as positiewe getalle is. Dit kan help om die breuke as desimale neer te skryf om jou te help om die getal te bereken. Vir die wortelvorms kan jy bereken tussen watter twee getalle die wortelvorm lê en dit gebruik om jou te help om die getalle te rangskik.<br>1. \\( \\frac{27}{7} \\approx 3,857 \\)<br>2. \\( \\sqrt{19} \\)<br>3. \\( 2\\pi \\approx 6,28 \\)<br>4. \\( -\\sqrt{\\frac{9}{4}} = -\\frac{3}{2} = -\\text{1,5} \\)<br>5. \\( -\\sqrt{8} \\) lê tussen \\( -2 \\) en \\( -3 \\)<br>6. \\( \\sqrt{51} \\) lê tussen \\( 7 \\) en \\( 8 \\)<br>Merk ook op dat \\( 0,45 < 0\\overline{45} \\)<br>Dan kry ons die volgende:<br> \\( -\\sqrt{8} \\ ; \\ -\\sqrt{\\frac{9}{4}} \\ ; \\ \\text{0,45} \\ ; \\ \\text{0,}\\overline{45} \\ ; \\ \\frac{27}{7} \\ ; \\ \\sqrt{19} \\ ; \\ 6 \\ ; \\ 2\\pi \\ ; \\ \\sqrt{51} \\)"}},"type":"multiple-choice"}],"childProblems":[{"id":"6009647939384c001eed980d","createdAt":"2021-01-21T11:24:41.589Z","updatedAt":"2021-01-21T11:24:41.589Z","deleted":false,"orderNumber":1,"courseId":"6009612f39384c001eed3400","problemId":"6009647939384c001eed980b","siyavulaNumber":"1.1","code":"ZSDLM","problem":{"en":{"latex":"\\( \\sqrt{18} \\)","html":"\\( \\sqrt{18} \\)"},"af":{"latex":"\\( \\sqrt{18} \\)","html":"\\( \\sqrt{18} \\)"}},"memo":{"en":{"latex":"\\( 4 \\text{ and } 5 ~(4^2 = 16 \\text{ and } 5^2=25) \\)","html":"\\( 4 \\text{ and } 5 ~(4^2 = 16 \\text{ and } 5^2=25) \\)"},"af":{"latex":"\\( 4 \\text{ en } 5 ~(4^2 = 16 \\text{ en } 5^2=25) \\)","html":"\\( 4 \\text{ en } 5 ~(4^2 = 16 \\text{ en } 5^2=25) \\)"}},"type":"multiple-choice"},{"id":"6009647b39384c001eed9815","createdAt":"2021-01-21T11:24:43.072Z","updatedAt":"2021-01-21T11:24:43.072Z","deleted":false,"orderNumber":2,"courseId":"6009612f39384c001eed3400","problemId":"6009647939384c001eed980b","siyavulaNumber":"1.1","code":"9THV7","problem":{"en":{"latex":"\\( \\sqrt[3]{81} \\)","html":"\\( \\sqrt[3]{81} \\)"},"af":{"latex":"\\( \\sqrt[3]{81} \\)","html":"\\( \\sqrt[3]{81} \\)"}},"memo":{"en":{"latex":"\\( 4 \\text{ and } 5~ (4^3 = 64 \\text{ and } 5^3=125) \\)","html":"\\( 4 \\text{ and } 5~ (4^3 = 64 \\text{ and } 5^3=125) \\)"},"af":{"latex":"\\( 4 \\text{ en } 5~ (4^3 = 64 \\text{ en } 5^3=125) \\)","html":"\\( 4 \\text{ en } 5~ (4^3 = 64 \\text{ en } 5^3=125) \\)"}},"type":"multiple-choice"},{"id":"6009647c39384c001eed981d","createdAt":"2021-01-21T11:24:44.603Z","updatedAt":"2021-01-21T11:24:44.603Z","deleted":false,"orderNumber":3,"courseId":"6009612f39384c001eed3400","problemId":"6009647939384c001eed980b","siyavulaNumber":"1.1","code":"Z7GWC","problem":{"en":{"latex":"\\( \\sqrt{29} \\)","html":"\\( \\sqrt{29} \\)"},"af":{"latex":"\\( \\sqrt{29} \\)","html":"\\( \\sqrt{29} \\)"}},"memo":{"en":{"latex":"\\( 5 \\text{ and } 6 ~(5^2 = 25 \\text{ and } 6^2=36) \\)","html":"\\( 5 \\text{ and } 6 ~(5^2 = 25 \\text{ and } 6^2=36) \\)"},"af":{"latex":"\\( 5 \\text{ en } 6 ~(5^2 = 25 \\text{ en } 6^2=36) \\)","html":"\\( 5 \\text{ en } 6 ~(5^2 = 25 \\text{ en } 6^2=36) \\)"}},"type":"multiple-choice"},{"id":"6009647e39384c001eed9825","createdAt":"2021-01-21T11:24:46.105Z","updatedAt":"2021-01-21T11:24:46.105Z","deleted":false,"orderNumber":4,"courseId":"6009612f39384c001eed3400","problemId":"6009647939384c001eed980b","siyavulaNumber":"1.1","code":"WVZK5","problem":{"en":{"latex":"\\( \\sqrt[3]{5} \\)","html":"\\( \\sqrt[3]{5} \\)"},"af":{"latex":"\\( \\sqrt[3]{5} \\)","html":"\\( \\sqrt[3]{5} \\)"}},"memo":{"en":{"latex":"\\( 1 \\text{ and } 2 ~(1^3 = 1 \\text{ and } 2^3=8) \\)","html":"\\( 1 \\text{ and } 2 ~(1^3 = 1 \\text{ and } 2^3=8) \\)"},"af":{"latex":"\\( 1 \\text{ en } 2 ~(1^3 = 1 \\text{ en } 2^3=8) \\)","html":"\\( 1 \\text{ en } 2 ~(1^3 = 1 \\text{ en } 2^3=8) \\)"}},"type":"multiple-choice"},{"id":"6009647f39384c001eed982d","createdAt":"2021-01-21T11:24:47.605Z","updatedAt":"2021-01-21T11:24:47.605Z","deleted":false,"orderNumber":5,"courseId":"6009612f39384c001eed3400","problemId":"6009647939384c001eed980b","siyavulaNumber":"1.1","code":"3H55V","problem":{"en":{"latex":"\\( \\sqrt[3]{79} \\)","html":"\\( \\sqrt[3]{79} \\)"},"af":{"latex":"\\( \\sqrt[3]{79} \\)","html":"\\( \\sqrt[3]{79} \\)"}},"memo":{"en":{"latex":"\\( 4 \\text{ and } 5~ (4^3 = 64 \\text{ and } 5^3=125) \\)","html":"\\( 4 \\text{ and } 5~ (4^3 = 64 \\text{ and } 5^3=125) \\)"},"af":{"latex":"\\( 4 \\text{ en } 5~ (4^3 = 64 \\text{ en } 5^3=125) \\)","html":"\\( 4 \\text{ en } 5~ (4^3 = 64 \\text{ en } 5^3=125) \\)"}},"type":"multiple-choice"},{"id":"6009648139384c001eed9835","createdAt":"2021-01-21T11:24:49.09Z","updatedAt":"2021-01-21T11:24:49.09Z","deleted":false,"orderNumber":6,"courseId":"6009612f39384c001eed3400","problemId":"6009647939384c001eed980b","siyavulaNumber":"1.1","code":"J3M8G","problem":{"en":{"latex":"\\( \\sqrt{155} \\)","html":"\\( \\sqrt{155} \\)"},"af":{"latex":"\\( \\sqrt{155} \\)","html":"\\( \\sqrt{155} \\)"}},"memo":{"en":{"latex":"\\( 12 \\text{ and } 13~ (12^2 = 144 \\text{ and } 13^2=169) \\)","html":"\\( 12 \\text{ and } 13~ (12^2 = 144 \\text{ and } 13^2=169) \\)"},"af":{"latex":"\\( 12 \\text{ en } 13~ (12^2 = 144 \\text{ en } 13^2=169) \\)","html":"\\( 12 \\text{ en } 13~ (12^2 = 144 \\text{ en } 13^2=169) \\)"}},"type":"multiple-choice"},{"id":"6009648239384c001eed983d","createdAt":"2021-01-21T11:24:50.591Z","updatedAt":"2021-01-21T11:24:50.591Z","deleted":false,"orderNumber":7,"courseId":"6009612f39384c001eed3400","problemId":"6009647939384c001eed980b","siyavulaNumber":"1.1","code":"S81OX","problem":{"en":{"latex":"\\( \\sqrt{57} \\)","html":"\\( \\sqrt{57} \\)"},"af":{"latex":"\\( \\sqrt{57} \\)","html":"\\( \\sqrt{57} \\)"}},"memo":{"en":{"latex":"\\( 7 \\text{ and } 8~ (7^2 = 49 \\text{ and } 8^2 = 64) \\)","html":"\\( 7 \\text{ and } 8~ (7^2 = 49 \\text{ and } 8^2 = 64) \\)"},"af":{"latex":"\\( 7 \\text{ en } 8~ (7^2 = 49 \\text{ en } 8^2 = 64) \\)","html":"\\( 7 \\text{ en } 8~ (7^2 = 49 \\text{ en } 8^2 = 64) \\)"}},"type":"multiple-choice"},{"id":"6009648439384c001eed9845","createdAt":"2021-01-21T11:24:52.178Z","updatedAt":"2021-01-21T11:24:52.178Z","deleted":false,"orderNumber":8,"courseId":"6009612f39384c001eed3400","problemId":"6009647939384c001eed980b","siyavulaNumber":"1.1","code":"FYKI3","problem":{"en":{"latex":"\\( \\sqrt{71} \\)","html":"\\( \\sqrt{71} \\)"},"af":{"latex":"\\( \\sqrt{71} \\)","html":"\\( \\sqrt{71} \\)"}},"memo":{"en":{"latex":"\\( 8 \\text{ and } 9~ (8^2 = 64 \\text{ and } 9^2 = 81) \\)","html":"\\( 8 \\text{ and } 9~ (8^2 = 64 \\text{ and } 9^2 = 81) \\)"},"af":{"latex":"\\( 8 \\text{ en } 9~ (8^2 = 64 \\text{ en } 9^2 = 81) \\)","html":"\\( 8 \\text{ en } 9~ (8^2 = 64 \\text{ en } 9^2 = 81) \\)"}},"type":"multiple-choice"},{"id":"6009648539384c001eed984d","createdAt":"2021-01-21T11:24:53.68Z","updatedAt":"2021-01-21T11:24:53.68Z","deleted":false,"orderNumber":9,"courseId":"6009612f39384c001eed3400","problemId":"6009647939384c001eed980b","siyavulaNumber":"1.1","code":"8P041","problem":{"en":{"latex":"\\( \\sqrt[3]{123} \\)","html":"\\( \\sqrt[3]{123} \\)"},"af":{"latex":"\\( \\sqrt[3]{123} \\)","html":"\\( \\sqrt[3]{123} \\)"}},"memo":{"en":{"latex":"\\( 4 \\text{ and } 5~ (4^3 = 64 \\text{ and } 5^3=125) \\)","html":"\\( 4 \\text{ and } 5~ (4^3 = 64 \\text{ and } 5^3=125) \\)"},"af":{"latex":"\\( 4 \\text{ en } 5~ (4^3 = 64 \\text{ en } 5^3=125) \\)","html":"\\( 4 \\text{ en } 5~ (4^3 = 64 \\text{ en } 5^3=125) \\)"}},"type":"multiple-choice"},{"id":"6009648739384c001eed9855","createdAt":"2021-01-21T11:24:55.176Z","updatedAt":"2021-01-21T11:24:55.176Z","deleted":false,"orderNumber":10,"courseId":"6009612f39384c001eed3400","problemId":"6009647939384c001eed980b","siyavulaNumber":"1.1","code":"X6V31","problem":{"en":{"latex":"\\( \\sqrt[3]{90} \\)","html":"\\( \\sqrt[3]{90} \\)"},"af":{"latex":"\\( \\sqrt[3]{90} \\)","html":"\\( \\sqrt[3]{90} \\)"}},"memo":{"en":{"latex":"\\( 4 \\text{ and } 5~ (4^3 = 64 \\text{ and } 5^3=125) \\)","html":"\\( 4 \\text{ and } 5~ (4^3 = 64 \\text{ and } 5^3=125) \\)"},"af":{"latex":"\\( 4 \\text{ en } 5~ (4^3 = 64 \\text{ en } 5^3=125) \\)","html":"\\( 4 \\text{ en } 5~ (4^3 = 64 \\text{ en } 5^3=125) \\)"}},"type":"multiple-choice"},{"id":"6009648939384c001eed985f","createdAt":"2021-01-21T11:24:57.091Z","updatedAt":"2021-01-21T11:24:57.091Z","deleted":false,"orderNumber":1,"courseId":"6009612f39384c001eed3400","problemId":"6009648839384c001eed985d","siyavulaNumber":"1.1","code":"D8R1A","problem":{"en":{"latex":"\\( \\sqrt{10} \\)","html":"\\( \\sqrt{10} \\)"},"af":{"latex":"\\( \\sqrt{10} \\)","html":"\\( \\sqrt{10} \\)"}},"memo":{"en":{"latex":"Since \\( 3^2 = 9 \\text{ and } 4^2 = 16 \\) , \\( \\sqrt{10} \\) must lie between \\( 3 \\) and \\( 4 \\) . But we note that \\( 10 \\) is<br>closer to \\( 9 \\) than to \\( 16 \\) and so \\( \\sqrt{10} \\) will be closer to \\( 3 \\) than to \\( 4 \\) .<br> \\( 3,1 \\) or \\( 3,2 \\) are suitable estimates.","html":"Since \\( 3^2 = 9 \\text{ and } 4^2 = 16 \\) , \\( \\sqrt{10} \\) must lie between \\( 3 \\) and \\( 4 \\) . But we note that \\( 10 \\) is<br>closer to \\( 9 \\) than to \\( 16 \\) and so \\( \\sqrt{10} \\) will be closer to \\( 3 \\) than to \\( 4 \\) .<br> \\( 3,1 \\) or \\( 3,2 \\) are suitable estimates."},"af":{"latex":"Aangesien \\( 3^2 = 9 \\text{ en } 4^2 = 16 \\) , moet \\( \\sqrt{10} \\) tussen \\( 3 \\) en \\( 4 \\) lê. Maar, ons merk op dat \\( 10 \\) nader aan \\( 9 \\) as aan \\( 16 \\) is en daarom sal \\( \\sqrt{10} \\) nader aan \\( 3 \\) wees as aan \\( 4 \\) .<br> \\( 3,1 \\) of \\( 3,2 \\) is gepaste skattings.","html":"Aangesien \\( 3^2 = 9 \\text{ en } 4^2 = 16 \\) , moet \\( \\sqrt{10} \\) tussen \\( 3 \\) en \\( 4 \\) lê. Maar, ons merk op dat \\( 10 \\) nader aan \\( 9 \\) as aan \\( 16 \\) is en daarom sal \\( \\sqrt{10} \\) nader aan \\( 3 \\) wees as aan \\( 4 \\) .<br> \\( 3,1 \\) of \\( 3,2 \\) is gepaste skattings."}},"type":"multiple-choice"},{"id":"6009648a39384c001eed9867","createdAt":"2021-01-21T11:24:58.571Z","updatedAt":"2021-01-21T11:24:58.571Z","deleted":false,"orderNumber":2,"courseId":"6009612f39384c001eed3400","problemId":"6009648839384c001eed985d","siyavulaNumber":"1.1","code":"DKLUW","problem":{"en":{"latex":"\\( \\sqrt{82} \\)","html":"\\( \\sqrt{82} \\)"},"af":{"latex":"\\( \\sqrt{82} \\)","html":"\\( \\sqrt{82} \\)"}},"memo":{"en":{"latex":"Since \\( 9^2 = 81 \\text{ and } 10^2 = 100 \\) , \\( \\sqrt{82} \\) must lie between \\( 9 \\) and \\( 10 \\) . But we note that \\( 82 \\) is closer to \\( 81 \\) than to \\( 100 \\) and so \\( \\sqrt{82} \\) will be closer to \\( 9 \\) than to 10.<br> \\( 9,1 \\) is a suitable estimate.","html":"Since \\( 9^2 = 81 \\text{ and } 10^2 = 100 \\) , \\( \\sqrt{82} \\) must lie between \\( 9 \\) and \\( 10 \\) . But we note that \\( 82 \\) is closer to \\( 81 \\) than to \\( 100 \\) and so \\( \\sqrt{82} \\) will be closer to \\( 9 \\) than to 10.<br> \\( 9,1 \\) is a suitable estimate."},"af":{"latex":"Aangesien \\( 9^2 = 81 \\text{ en } 10^2 = 100 \\) , moet \\( \\sqrt{82} \\) tussen \\( 9 \\) en \\( 10 \\) lê. Maar, ons merk op dat \\( 82 \\) nader aan \\( 81 \\) as aan \\( 100 \\) is en daarom sal \\( \\sqrt{82} \\) nader aan \\( 3 \\) wees as aan \\( 9 \\) .<br> \\( 9,1 \\) is 'n gepaste skatting.","html":"Aangesien \\( 9^2 = 81 \\text{ en } 10^2 = 100 \\) , moet \\( \\sqrt{82} \\) tussen \\( 9 \\) en \\( 10 \\) lê. Maar, ons merk op dat \\( 82 \\) nader aan \\( 81 \\) as aan \\( 100 \\) is en daarom sal \\( \\sqrt{82} \\) nader aan \\( 3 \\) wees as aan \\( 9 \\) .<br> \\( 9,1 \\) is 'n gepaste skatting."}},"type":"multiple-choice"},{"id":"6009648c39384c001eed986f","createdAt":"2021-01-21T11:25:00.058Z","updatedAt":"2021-01-21T11:25:00.058Z","deleted":false,"orderNumber":3,"courseId":"6009612f39384c001eed3400","problemId":"6009648839384c001eed985d","siyavulaNumber":"1.1","code":"P9X5T","problem":{"en":{"latex":"\\( \\sqrt{15} \\)","html":"\\( \\sqrt{15} \\)"},"af":{"latex":"\\( \\sqrt{15} \\)","html":"\\( \\sqrt{15} \\)"}},"memo":{"en":{"latex":"Since \\( 3^2 = 9 \\text{ and } 4^2 = 16 \\) , \\( \\sqrt{15} \\) must lie between \\( 3 \\) and \\( 4 \\) . But we note that \\( 15 \\) is closer to \\( 16 \\) than to \\( 9 \\) and so \\( \\sqrt{15} \\) will be closer to \\( 4 \\) than to \\( 3 \\) .<br> \\( 3,9 \\) is a suitable estimate.","html":"Since \\( 3^2 = 9 \\text{ and } 4^2 = 16 \\) , \\( \\sqrt{15} \\) must lie between \\( 3 \\) and \\( 4 \\) . But we note that \\( 15 \\) is closer to \\( 16 \\) than to \\( 9 \\) and so \\( \\sqrt{15} \\) will be closer to \\( 4 \\) than to \\( 3 \\) .<br> \\( 3,9 \\) is a suitable estimate."},"af":{"latex":"Aangesien \\( 3^2 = 9 \\text{ en } 4^2 = 16 \\) , moet \\( \\sqrt{15} \\) tussen \\( 3 \\) en \\( 4 \\) lê.<br>Maar, ons merk op dat \\( 15 \\) nader aan \\( 16 \\) as aan \\( 9 \\) is en daarom sal \\( \\sqrt{15} \\) nader aan \\( 4 \\) wees as aan \\( 3 \\) .<br> \\( 3,9 \\) is 'n gepaste skatting.","html":"Aangesien \\( 3^2 = 9 \\text{ en } 4^2 = 16 \\) , moet \\( \\sqrt{15} \\) tussen \\( 3 \\) en \\( 4 \\) lê.<br>Maar, ons merk op dat \\( 15 \\) nader aan \\( 16 \\) as aan \\( 9 \\) is en daarom sal \\( \\sqrt{15} \\) nader aan \\( 4 \\) wees as aan \\( 3 \\) .<br> \\( 3,9 \\) is 'n gepaste skatting."}},"type":"multiple-choice"},{"id":"6009648d39384c001eed9877","createdAt":"2021-01-21T11:25:01.551Z","updatedAt":"2021-01-21T11:25:01.551Z","deleted":false,"orderNumber":4,"courseId":"6009612f39384c001eed3400","problemId":"6009648839384c001eed985d","siyavulaNumber":"1.1","code":"7ZUQZ","problem":{"en":{"latex":"\\( \\sqrt{90} \\)","html":"\\( \\sqrt{90} \\)"},"af":{"latex":"\\( \\sqrt{90} \\)","html":"\\( \\sqrt{90} \\)"}},"memo":{"en":{"latex":"Since \\( 9^2 = 81 \\text{ and } 10^2 = 100 \\) , \\( \\sqrt{90} \\) must lie between \\( 9 \\) and \\( 10 \\) . But we note that 90 is about halfway between \\( 81 \\) and \\( 100 \\) , so \\( \\sqrt{90} \\) will be halfway between \\( 9 \\) and \\( 10 \\) .<br> \\( 9,5 \\) is a suitable estimate.","html":"Since \\( 9^2 = 81 \\text{ and } 10^2 = 100 \\) , \\( \\sqrt{90} \\) must lie between \\( 9 \\) and \\( 10 \\) . But we note that 90 is about halfway between \\( 81 \\) and \\( 100 \\) , so \\( \\sqrt{90} \\) will be halfway between \\( 9 \\) and \\( 10 \\) .<br> \\( 9,5 \\) is a suitable estimate."},"af":{"latex":"Aangesien \\( 9^2 = 81 \\text{ en } 10^2 = 100 \\) , moet \\( \\sqrt{90} \\) tussen \\( 9 \\) en \\( 10 \\) lê. Maar, ons merk op dat \\( 90 \\) omtrent halfpad tussen \\( 81 \\) en \\( 100 \\) is en daarom sal \\( \\sqrt{90} \\) halfpad tussen \\( 9 \\) en \\( 10 \\) wees.<br> \\( 9,5 \\) is 'n gepaste skatting.","html":"Aangesien \\( 9^2 = 81 \\text{ en } 10^2 = 100 \\) , moet \\( \\sqrt{90} \\) tussen \\( 9 \\) en \\( 10 \\) lê. Maar, ons merk op dat \\( 90 \\) omtrent halfpad tussen \\( 81 \\) en \\( 100 \\) is en daarom sal \\( \\sqrt{90} \\) halfpad tussen \\( 9 \\) en \\( 10 \\) wees.<br> \\( 9,5 \\) is 'n gepaste skatting."}},"type":"multiple-choice"}],"permutationProblems":[],"permutationChildProblems":[],"problemImages":[],"problemVideos":[{"id":"6090fd72f6a894001fd9787a","createdAt":"2021-05-04T07:53:22.402Z","updatedAt":"2021-05-04T07:53:22.402Z","deleted":false,"videoId":"5f8d978bdf26d44466082eaf","problemId":"6009647939384c001eed980d"},{"id":"6090fd8df6a894001fd9787c","createdAt":"2021-05-04T07:53:49.023Z","updatedAt":"2021-05-04T07:53:49.023Z","deleted":false,"videoId":"5f8d995adf26d44466083613","problemId":"6009647b39384c001eed9815"},{"id":"6090fda0f6a894001fd97880","createdAt":"2021-05-04T07:54:08.338Z","updatedAt":"2021-05-04T07:54:08.338Z","deleted":false,"videoId":"5f8d993edf26d44466083598","problemId":"6009647c39384c001eed981d"},{"id":"6090fdadf6a894001fd97882","createdAt":"2021-05-04T07:54:21.961Z","updatedAt":"2021-05-04T07:54:21.961Z","deleted":false,"videoId":"5f8d9938df26d44466083581","problemId":"6009647e39384c001eed9825"},{"id":"6090fdd1f6a894001fd97886","createdAt":"2021-05-04T07:54:57.366Z","updatedAt":"2021-05-04T07:54:57.366Z","deleted":false,"videoId":"5f8d9aabdf26d44466083b85","problemId":"6009647f39384c001eed982d"},{"id":"6090fde0f6a894001fd9788a","createdAt":"2021-05-04T07:55:12.298Z","updatedAt":"2021-05-04T07:55:12.298Z","deleted":false,"videoId":"5f8d9b17df26d44466083d40","problemId":"6009648139384c001eed9835"},{"id":"6090fdeff6a894001fd9788c","createdAt":"2021-05-04T07:55:27.503Z","updatedAt":"2021-05-04T07:55:27.503Z","deleted":false,"videoId":"5f8d9b7fdf26d44466083edd","problemId":"6009648239384c001eed983d"},{"id":"6090fdfdf6a894001fd97890","createdAt":"2021-05-04T07:55:41.139Z","updatedAt":"2021-05-04T07:55:41.139Z","deleted":false,"videoId":"5f8d9a0ddf26d444660838ee","problemId":"6009648439384c001eed9845"},{"id":"6090fe1cf6a894001fd97896","createdAt":"2021-05-04T07:56:12.359Z","updatedAt":"2021-05-04T07:56:12.359Z","deleted":false,"videoId":"5f8d9abbdf26d44466083bc6","problemId":"6009648539384c001eed984d"},{"id":"6090fe30f6a894001fd9789b","createdAt":"2021-05-04T07:56:32.07Z","updatedAt":"2021-05-04T07:56:32.07Z","deleted":false,"videoId":"5f8d981adf26d444660830fe","problemId":"6009648739384c001eed9855"},{"id":"6090feb3f6a894001fd978a1","createdAt":"2021-05-04T07:58:43.338Z","updatedAt":"2021-05-04T07:58:43.338Z","deleted":false,"videoId":"5f8d99c9df26d444660837e2","problemId":"6009648939384c001eed985f"},{"id":"6090fec0f6a894001fd978a3","createdAt":"2021-05-04T07:58:56.112Z","updatedAt":"2021-05-04T07:58:56.112Z","deleted":false,"videoId":"5f8d97f9df26d44466083079","problemId":"6009648a39384c001eed9867"},{"id":"6090fecff6a894001fd978a7","createdAt":"2021-05-04T07:59:11.291Z","updatedAt":"2021-05-04T07:59:11.291Z","deleted":false,"videoId":"5f8d975cdf26d44466082de2","problemId":"6009648c39384c001eed986f"},{"id":"6090fedaf6a894001fd978a9","createdAt":"2021-05-04T07:59:22.112Z","updatedAt":"2021-05-04T07:59:22.112Z","deleted":false,"videoId":"5f8d9a1ddf26d4446608392f","problemId":"6009648d39384c001eed9877"},{"id":"6090fef9f6a894001fd978ad","createdAt":"2021-05-04T07:59:53.22Z","updatedAt":"2021-05-04T07:59:53.22Z","deleted":false,"videoId":"5f8d99e0df26d44466083841","problemId":"6009648f39384c001eed987f"}],"solutions":[{"id":"6009647939384c001eed980f","createdAt":"2021-01-21T11:24:41.963Z","updatedAt":"2021-01-21T11:24:41.963Z","deleted":false,"problemId":"6009647939384c001eed980d","solution":{"en":{"latex":"\\( 4 \\text{ and } 5 \\)","html":"\\( 4 \\text{ and } 5 \\)"},"af":{"latex":"\\( 4 \\text{ en } 5 \\)","html":"\\( 4 \\text{ en } 5 \\)"}},"correct":true},{"id":"6009647a39384c001eed9811","createdAt":"2021-01-21T11:24:42.333Z","updatedAt":"2021-01-21T11:24:42.333Z","deleted":false,"problemId":"6009647939384c001eed980d","solution":{"en":{"latex":"\\( 3 \\text{ and } 4 \\)","html":"\\( 3 \\text{ and } 4 \\)"},"af":{"latex":"\\( 3 \\text{ en } 4 \\)","html":"\\( 3 \\text{ en } 4 \\)"}},"correct":false},{"id":"6009647a39384c001eed9813","createdAt":"2021-01-21T11:24:42.697Z","updatedAt":"2021-01-21T11:24:42.697Z","deleted":false,"problemId":"6009647939384c001eed980d","solution":{"en":{"latex":"\\( 5 \\text{ and } 6 \\)","html":"\\( 5 \\text{ and } 6 \\)"},"af":{"latex":"\\( 5 \\text{ en } 6 \\)","html":"\\( 5 \\text{ en } 6 \\)"}},"correct":false},{"id":"6009647b39384c001eed9817","createdAt":"2021-01-21T11:24:43.445Z","updatedAt":"2021-01-28T15:54:58.234Z","deleted":false,"problemId":"6009647b39384c001eed9815","solution":{"af":{"html":"\\( 4 \\text{ en } 5~ (4^3 = 64 \\text{ en } 5^3=125) \\)","latex":"\\( 4 \\text{ en } 5~ (4^3 = 64 \\text{ en } 5^3=125) \\)"},"en":{"html":"\\( 4 \\text{ and } 5~  \\)","latex":"\\( 4 \\text{ and } 5~  \\)"}},"correct":true},{"id":"6009647b39384c001eed9819","createdAt":"2021-01-21T11:24:43.827Z","updatedAt":"2021-01-21T11:24:43.827Z","deleted":false,"problemId":"6009647b39384c001eed9815","solution":{"en":{"latex":"\\( 2 \\text{ and } 3 \\)","html":"\\( 2 \\text{ and } 3 \\)"},"af":{"latex":"\\( 2 \\text{ en } 3 \\)","html":"\\( 2 \\text{ en } 3 \\)"}},"correct":false},{"id":"6009647c39384c001eed981b","createdAt":"2021-01-21T11:24:44.217Z","updatedAt":"2021-01-21T11:24:44.217Z","deleted":false,"problemId":"6009647b39384c001eed9815","solution":{"en":{"latex":"\\( 6 \\text{ and } 7 \\)","html":"\\( 6 \\text{ and } 7 \\)"},"af":{"latex":"\\( 6 \\text{ en } 7 \\)","html":"\\( 6 \\text{ en } 7 \\)"}},"correct":false},{"id":"6009647c39384c001eed981f","createdAt":"2021-01-21T11:24:44.97Z","updatedAt":"2021-01-21T11:24:44.97Z","deleted":false,"problemId":"6009647c39384c001eed981d","solution":{"en":{"latex":"\\( 5 \\text{ and } 6 \\)","html":"\\( 5 \\text{ and } 6 \\)"},"af":{"latex":"\\( 5 \\text{ en } 6 \\)","html":"\\( 5 \\text{ en } 6 \\)"}},"correct":true},{"id":"6009647d39384c001eed9821","createdAt":"2021-01-21T11:24:45.339Z","updatedAt":"2021-01-21T11:24:45.339Z","deleted":false,"problemId":"6009647c39384c001eed981d","solution":{"en":{"latex":"\\( 4 \\text{ and } 5 \\)","html":"\\( 4 \\text{ and } 5 \\)"},"af":{"latex":"\\( 4 \\text{ en } 5 \\)","html":"\\( 4 \\text{ en } 5 \\)"}},"correct":false},{"id":"6009647d39384c001eed9823","createdAt":"2021-01-21T11:24:45.715Z","updatedAt":"2021-01-21T11:24:45.715Z","deleted":false,"problemId":"6009647c39384c001eed981d","solution":{"en":{"latex":"\\( 6 \\text{ and } 7 \\)","html":"\\( 6 \\text{ and } 7 \\)"},"af":{"latex":"\\( 6 \\text{ en } 7 \\)","html":"\\( 6 \\text{ en } 7 \\)"}},"correct":false},{"id":"6009647e39384c001eed9827","createdAt":"2021-01-21T11:24:46.476Z","updatedAt":"2021-01-21T11:24:46.476Z","deleted":false,"problemId":"6009647e39384c001eed9825","solution":{"en":{"latex":"\\( 1 \\text{ and } 2 \\)","html":"\\( 1 \\text{ and } 2 \\)"},"af":{"latex":"\\( 1 \\text{ en } 2 \\)","html":"\\( 1 \\text{ en } 2 \\)"}},"correct":true},{"id":"6009647e39384c001eed9829","createdAt":"2021-01-21T11:24:46.847Z","updatedAt":"2021-01-21T11:24:46.847Z","deleted":false,"problemId":"6009647e39384c001eed9825","solution":{"en":{"latex":"\\( 0 \\text{ and } 1 \\)","html":"\\( 0 \\text{ and } 1 \\)"},"af":{"latex":"\\( 0 \\text{ en } 1 \\)","html":"\\( 0 \\text{ en } 1 \\)"}},"correct":false},{"id":"6009647f39384c001eed982b","createdAt":"2021-01-21T11:24:47.218Z","updatedAt":"2021-01-21T11:24:47.218Z","deleted":false,"problemId":"6009647e39384c001eed9825","solution":{"en":{"latex":"\\( 2 \\text{ and } 3 \\)","html":"\\( 2 \\text{ and } 3 \\)"},"af":{"latex":"\\( 2 \\text{ en } 3 \\)","html":"\\( 2 \\text{ en } 3 \\)"}},"correct":false},{"id":"6009647f39384c001eed982f","createdAt":"2021-01-21T11:24:47.973Z","updatedAt":"2021-01-21T11:24:47.973Z","deleted":false,"problemId":"6009647f39384c001eed982d","solution":{"en":{"latex":"\\( 4 \\text{ and } 5 \\)","html":"\\( 4 \\text{ and } 5 \\)"},"af":{"latex":"\\( 4 \\text{ en } 5 \\)","html":"\\( 4 \\text{ en } 5 \\)"}},"correct":true},{"id":"6009648039384c001eed9831","createdAt":"2021-01-21T11:24:48.346Z","updatedAt":"2021-01-21T11:24:48.346Z","deleted":false,"problemId":"6009647f39384c001eed982d","solution":{"en":{"latex":"\\( 3 \\text{ and } 4 \\)","html":"\\( 3 \\text{ and } 4 \\)"},"af":{"latex":"\\( 3 \\text{ en } 4 \\)","html":"\\( 3 \\text{ en } 4 \\)"}},"correct":false},{"id":"6009648039384c001eed9833","createdAt":"2021-01-21T11:24:48.712Z","updatedAt":"2021-01-21T11:24:48.712Z","deleted":false,"problemId":"6009647f39384c001eed982d","solution":{"en":{"latex":"\\( 5 \\text{ and } 6 \\)","html":"\\( 5 \\text{ and } 6 \\)"},"af":{"latex":"\\( 5 \\text{ en } 6 \\)","html":"\\( 5 \\text{ en } 6 \\)"}},"correct":false},{"id":"6009648139384c001eed9837","createdAt":"2021-01-21T11:24:49.463Z","updatedAt":"2021-01-21T11:24:49.463Z","deleted":false,"problemId":"6009648139384c001eed9835","solution":{"en":{"latex":"\\( 12 \\text{ and } 13 \\)","html":"\\( 12 \\text{ and } 13 \\)"},"af":{"latex":"\\( 12 \\text{ en } 13 \\)","html":"\\( 12 \\text{ en } 13 \\)"}},"correct":true},{"id":"6009648139384c001eed9839","createdAt":"2021-01-21T11:24:49.826Z","updatedAt":"2021-01-21T11:24:49.826Z","deleted":false,"problemId":"6009648139384c001eed9835","solution":{"en":{"latex":"\\( 11 \\text{ and } 12 \\)","html":"\\( 11 \\text{ and } 12 \\)"},"af":{"latex":"\\( 11 \\text{ en } 12 \\)","html":"\\( 11 \\text{ en } 12 \\)"}},"correct":false},{"id":"6009648239384c001eed983b","createdAt":"2021-01-21T11:24:50.196Z","updatedAt":"2021-01-21T11:24:50.196Z","deleted":false,"problemId":"6009648139384c001eed9835","solution":{"en":{"latex":"\\( 13 \\text{ and } 14 \\)","html":"\\( 13 \\text{ and } 14 \\)"},"af":{"latex":"\\( 13 \\text{ en } 14 \\)","html":"\\( 13 \\text{ en } 14 \\)"}},"correct":false},{"id":"6009648339384c001eed983f","createdAt":"2021-01-21T11:24:51.042Z","updatedAt":"2021-01-21T11:24:51.042Z","deleted":false,"problemId":"6009648239384c001eed983d","solution":{"en":{"latex":"\\( 7 \\text{ and } 8 \\)","html":"\\( 7 \\text{ and } 8 \\)"},"af":{"latex":"\\( 7 \\text{ en } 8 \\)","html":"\\( 7 \\text{ en } 8 \\)"}},"correct":true},{"id":"6009648339384c001eed9841","createdAt":"2021-01-21T11:24:51.422Z","updatedAt":"2021-01-21T11:24:51.422Z","deleted":false,"problemId":"6009648239384c001eed983d","solution":{"en":{"latex":"\\( 6 \\text{ and } 7 \\)","html":"\\( 6 \\text{ and } 7 \\)"},"af":{"latex":"\\( 6 \\text{ en } 7 \\)","html":"\\( 6 \\text{ en } 7 \\)"}},"correct":false},{"id":"6009648339384c001eed9843","createdAt":"2021-01-21T11:24:51.792Z","updatedAt":"2021-01-21T11:24:51.792Z","deleted":false,"problemId":"6009648239384c001eed983d","solution":{"en":{"latex":"\\( 8 \\text{ and } 9 \\)","html":"\\( 8 \\text{ and } 9 \\)"},"af":{"latex":"\\( 8 \\text{ en } 9 \\)","html":"\\( 8 \\text{ en } 9 \\)"}},"correct":false},{"id":"6009648439384c001eed9847","createdAt":"2021-01-21T11:24:52.55Z","updatedAt":"2021-01-21T11:24:52.55Z","deleted":false,"problemId":"6009648439384c001eed9845","solution":{"en":{"latex":"\\( 8 \\text{ and } 9 \\)","html":"\\( 8 \\text{ and } 9 \\)"},"af":{"latex":"\\( 8 \\text{ en } 9 \\)","html":"\\( 8 \\text{ en } 9 \\)"}},"correct":true},{"id":"6009648439384c001eed9849","createdAt":"2021-01-21T11:24:52.924Z","updatedAt":"2021-01-21T11:24:52.924Z","deleted":false,"problemId":"6009648439384c001eed9845","solution":{"en":{"latex":"\\( 7 \\text{ and } 8 \\)","html":"\\( 7 \\text{ and } 8 \\)"},"af":{"latex":"\\( 7 \\text{ en } 8 \\)","html":"\\( 7 \\text{ en } 8 \\)"}},"correct":false},{"id":"6009648539384c001eed984b","createdAt":"2021-01-21T11:24:53.296Z","updatedAt":"2021-01-21T11:24:53.296Z","deleted":false,"problemId":"6009648439384c001eed9845","solution":{"en":{"latex":"\\( 9 \\text{ and } 10 \\)","html":"\\( 9 \\text{ and } 10 \\)"},"af":{"latex":"\\( 9 \\text{ en } 10 \\)","html":"\\( 9 \\text{ en } 10 \\)"}},"correct":false},{"id":"6009648639384c001eed984f","createdAt":"2021-01-21T11:24:54.049Z","updatedAt":"2021-01-28T15:56:30.479Z","deleted":false,"problemId":"6009648539384c001eed984d","solution":{"af":{"html":"\\( 4 \\text{ en } 5~ (4^3 = 64 \\text{ en } 5^3=125) \\)","latex":"\\( 4 \\text{ en } 5~ (4^3 = 64 \\text{ en } 5^3=125) \\)"},"en":{"html":"\\( 4 \\text{ and } 5~ \\)","latex":"\\( 4 \\text{ and } 5~ \\)"}},"correct":true},{"id":"6009648639384c001eed9851","createdAt":"2021-01-21T11:24:54.421Z","updatedAt":"2021-01-21T11:24:54.421Z","deleted":false,"problemId":"6009648539384c001eed984d","solution":{"en":{"latex":"\\( 3 \\text{ and } 4 \\)","html":"\\( 3 \\text{ and } 4 \\)"},"af":{"latex":"\\( 3 \\text{ en } 4 \\)","html":"\\( 3 \\text{ en } 4 \\)"}},"correct":false},{"id":"6009648639384c001eed9853","createdAt":"2021-01-21T11:24:54.793Z","updatedAt":"2021-01-21T11:24:54.793Z","deleted":false,"problemId":"6009648539384c001eed984d","solution":{"en":{"latex":"\\( 5 \\text{ and } 6 \\)","html":"\\( 5 \\text{ and } 6 \\)"},"af":{"latex":"\\( 5 \\text{ en } 6 \\)","html":"\\( 5 \\text{ en } 6 \\)"}},"correct":false},{"id":"6009648739384c001eed9857","createdAt":"2021-01-21T11:24:55.564Z","updatedAt":"2021-01-21T11:24:55.564Z","deleted":false,"problemId":"6009648739384c001eed9855","solution":{"en":{"latex":"\\( 4 \\text{ and } 5 \\)","html":"\\( 4 \\text{ and } 5 \\)"},"af":{"latex":"\\( 4 \\text{ en } 5 \\)","html":"\\( 4 \\text{ en } 5 \\)"}},"correct":true},{"id":"6009648739384c001eed9859","createdAt":"2021-01-21T11:24:55.95Z","updatedAt":"2021-01-21T11:24:55.95Z","deleted":false,"problemId":"6009648739384c001eed9855","solution":{"en":{"latex":"\\( 1 \\text{ and } 2 \\)","html":"\\( 1 \\text{ and } 2 \\)"},"af":{"latex":"\\( 1 \\text{ en } 2 \\)","html":"\\( 1 \\text{ en } 2 \\)"}},"correct":false},{"id":"6009648839384c001eed985b","createdAt":"2021-01-21T11:24:56.315Z","updatedAt":"2021-01-21T11:24:56.315Z","deleted":false,"problemId":"6009648739384c001eed9855","solution":{"en":{"latex":"\\( 3 \\text{ and } 4 \\)","html":"\\( 3 \\text{ and } 4 \\)"},"af":{"latex":"\\( 3 \\text{ en } 4 \\)","html":"\\( 3 \\text{ en } 4 \\)"}},"correct":false},{"id":"6009648939384c001eed9861","createdAt":"2021-01-21T11:24:57.46Z","updatedAt":"2021-01-21T11:24:57.46Z","deleted":false,"problemId":"6009648939384c001eed985f","solution":{"en":{"latex":"\\( 3,1 \\text{ or } 3,2 \\)","html":"\\( 3,1 \\text{ or } 3,2 \\)"},"af":{"latex":"\\( 3,1 \\text{ of } 3,2 \\)","html":"\\( 3,1 \\text{ of } 3,2 \\)"}},"correct":true},{"id":"6009648939384c001eed9863","createdAt":"2021-01-21T11:24:57.823Z","updatedAt":"2021-01-21T11:24:57.823Z","deleted":false,"problemId":"6009648939384c001eed985f","solution":{"en":{"latex":"\\( 2,9 \\)","html":"\\( 2,9 \\)"},"af":{"latex":"\\( 2,9 \\)","html":"\\( 2,9 \\)"}},"correct":false},{"id":"6009648a39384c001eed9865","createdAt":"2021-01-21T11:24:58.19Z","updatedAt":"2021-01-21T11:24:58.19Z","deleted":false,"problemId":"6009648939384c001eed985f","solution":{"en":{"latex":"\\( 3,6 \\)","html":"\\( 3,6 \\)"},"af":{"latex":"\\( 3,6 \\)","html":"\\( 3,6 \\)"}},"correct":false},{"id":"6009648a39384c001eed9869","createdAt":"2021-01-21T11:24:58.943Z","updatedAt":"2021-01-21T11:24:58.943Z","deleted":false,"problemId":"6009648a39384c001eed9867","solution":{"en":{"latex":"\\( 9,1 \\)","html":"\\( 9,1 \\)"},"af":{"latex":"\\( 9,1 \\)","html":"\\( 9,1 \\)"}},"correct":true},{"id":"6009648b39384c001eed986b","createdAt":"2021-01-21T11:24:59.306Z","updatedAt":"2021-01-21T11:24:59.306Z","deleted":false,"problemId":"6009648a39384c001eed9867","solution":{"en":{"latex":"\\( 9,5 \\)","html":"\\( 9,5 \\)"},"af":{"latex":"\\( 9,5 \\)","html":"\\( 9,5 \\)"}},"correct":false},{"id":"6009648b39384c001eed986d","createdAt":"2021-01-21T11:24:59.676Z","updatedAt":"2021-01-21T11:24:59.676Z","deleted":false,"problemId":"6009648a39384c001eed9867","solution":{"en":{"latex":"\\( 8.5 \\)","html":"\\( 8.5 \\)"},"af":{"latex":"\\( 8.5 \\)","html":"\\( 8.5 \\)"}},"correct":false},{"id":"6009648c39384c001eed9871","createdAt":"2021-01-21T11:25:00.433Z","updatedAt":"2021-01-21T11:25:00.433Z","deleted":false,"problemId":"6009648c39384c001eed986f","solution":{"en":{"latex":"\\( 3,9 \\)","html":"\\( 3,9 \\)"},"af":{"latex":"\\( 3,9 \\)","html":"\\( 3,9 \\)"}},"correct":true},{"id":"6009648c39384c001eed9873","createdAt":"2021-01-21T11:25:00.797Z","updatedAt":"2021-01-21T11:25:00.797Z","deleted":false,"problemId":"6009648c39384c001eed986f","solution":{"en":{"latex":"\\( 4,9 \\)","html":"\\( 4,9 \\)"},"af":{"latex":"\\( 4,9 \\)","html":"\\( 4,9 \\)"}},"correct":false},{"id":"6009648d39384c001eed9875","createdAt":"2021-01-21T11:25:01.163Z","updatedAt":"2021-01-21T11:25:01.163Z","deleted":false,"problemId":"6009648c39384c001eed986f","solution":{"en":{"latex":"\\( 3,2 \\)","html":"\\( 3,2 \\)"},"af":{"latex":"\\( 3,2 \\)","html":"\\( 3,2 \\)"}},"correct":false},{"id":"6009648d39384c001eed9879","createdAt":"2021-01-21T11:25:01.926Z","updatedAt":"2021-01-21T11:25:01.926Z","deleted":false,"problemId":"6009648d39384c001eed9877","solution":{"en":{"latex":"\\( 9,5 \\)","html":"\\( 9,5 \\)"},"af":{"latex":"\\( 9,5 \\)","html":"\\( 9,5 \\)"}},"correct":true},{"id":"6009648e39384c001eed987b","createdAt":"2021-01-21T11:25:02.291Z","updatedAt":"2021-01-21T11:25:02.291Z","deleted":false,"problemId":"6009648d39384c001eed9877","solution":{"en":{"latex":"\\( 9,6 \\)","html":"\\( 9,6 \\)"},"af":{"latex":"\\( 9,6 \\)","html":"\\( 9,6 \\)"}},"correct":false},{"id":"6009648e39384c001eed987d","createdAt":"2021-01-21T11:25:02.66Z","updatedAt":"2021-01-21T11:25:02.66Z","deleted":false,"problemId":"6009648d39384c001eed9877","solution":{"en":{"latex":"\\( 9,9 \\)","html":"\\( 9,9 \\)"},"af":{"latex":"\\( 9,9 \\)","html":"\\( 9,9 \\)"}},"correct":false},{"id":"6009648f39384c001eed9881","createdAt":"2021-01-21T11:25:03.41Z","updatedAt":"2021-01-21T11:25:03.41Z","deleted":false,"problemId":"6009648f39384c001eed987f","solution":{"en":{"latex":"\\( -\\sqrt{8} \\ ; \\ -\\sqrt{\\frac{9}{4}} \\ ; \\ \\text{0,45} \\ ; \\ \\text{0,}\\overline{45} \\ ; \\ \\frac{27}{7} \\ ; \\ \\sqrt{19} \\ ; \\ 6 \\ ; \\ 2\\pi \\ ; \\ \\sqrt{51} \\)","html":"\\( -\\sqrt{8} \\ ; \\ -\\sqrt{\\frac{9}{4}} \\ ; \\ \\text{0,45} \\ ; \\ \\text{0,}\\overline{45} \\ ; \\ \\frac{27}{7} \\ ; \\ \\sqrt{19} \\ ; \\ 6 \\ ; \\ 2\\pi \\ ; \\ \\sqrt{51} \\)"},"af":{"latex":"\\( -\\sqrt{8} \\ ; \\ -\\sqrt{\\frac{9}{4}} \\ ; \\ \\text{0,45} \\ ; \\ \\text{0,}\\overline{45} \\ ; \\ \\frac{27}{7} \\ ; \\ \\sqrt{19} \\ ; \\ 6 \\ ; \\ 2\\pi \\ ; \\ \\sqrt{51} \\)","html":"\\( -\\sqrt{8} \\ ; \\ -\\sqrt{\\frac{9}{4}} \\ ; \\ \\text{0,45} \\ ; \\ \\text{0,}\\overline{45} \\ ; \\ \\frac{27}{7} \\ ; \\ \\sqrt{19} \\ ; \\ 6 \\ ; \\ 2\\pi \\ ; \\ \\sqrt{51} \\)"}},"correct":true},{"id":"6009648f39384c001eed9883","createdAt":"2021-01-21T11:25:03.779Z","updatedAt":"2021-01-21T11:25:03.779Z","deleted":false,"problemId":"6009648f39384c001eed987f","solution":{"en":{"latex":"\\( -\\sqrt{8} \\ ; \\ -\\sqrt{\\frac{9}{4}} \\ ; \\ 2\\pi \\ ; \\ \\text{0,}\\overline{45} ; \\ -\\frac{27}{7} \\ ; \\ \\sqrt{19} \\ ; \\ 6 \\ ; \\ \\text{0,45} \\ ; \\ \\sqrt{51} \\)","html":"\\( -\\sqrt{8} \\ ; \\ -\\sqrt{\\frac{9}{4}} \\ ; \\ 2\\pi \\ ; \\ \\text{0,}\\overline{45} ; \\ -\\frac{27}{7} \\ ; \\ \\sqrt{19} \\ ; \\ 6 \\ ; \\ \\text{0,45} \\ ; \\ \\sqrt{51} \\)"},"af":{"latex":"\\( -\\sqrt{8} \\ ; \\ -\\sqrt{\\frac{9}{4}} \\ ; \\ 2\\pi \\ ; \\ \\text{0,}\\overline{45} ; \\ -\\frac{27}{7} \\ ; \\ \\sqrt{19} \\ ; \\ 6 \\ ; \\ \\text{0,45} \\ ; \\ \\sqrt{51} \\)","html":"\\( -\\sqrt{8} \\ ; \\ -\\sqrt{\\frac{9}{4}} \\ ; \\ 2\\pi \\ ; \\ \\text{0,}\\overline{45} ; \\ -\\frac{27}{7} \\ ; \\ \\sqrt{19} \\ ; \\ 6 \\ ; \\ \\text{0,45} \\ ; \\ \\sqrt{51} \\)"}},"correct":false},{"id":"6009649039384c001eed9885","createdAt":"2021-01-21T11:25:04.153Z","updatedAt":"2021-01-21T11:25:04.153Z","deleted":false,"problemId":"6009648f39384c001eed987f","solution":{"en":{"latex":"\\( -\\sqrt{8} \\ ; \\ \\sqrt{19}\\ ; \\ \\text{0,45} \\ ; \\ \\text{0,}\\overline{45} ; \\ \\frac{27}{7} \\ ; \\ -\\sqrt{\\frac{9}{4}} \\ ; \\ 6 \\ ; \\ 2\\pi \\ ; \\ \\sqrt{51} \\)","html":"\\( -\\sqrt{8} \\ ; \\ \\sqrt{19}\\ ; \\ \\text{0,45} \\ ; \\ \\text{0,}\\overline{45} ; \\ \\frac{27}{7} \\ ; \\ -\\sqrt{\\frac{9}{4}} \\ ; \\ 6 \\ ; \\ 2\\pi \\ ; \\ \\sqrt{51} \\)"},"af":{"latex":"\\( -\\sqrt{8} \\ ; \\ \\sqrt{19}\\ ; \\ \\text{0,45} \\ ; \\ \\text{0,}\\overline{45} ; \\ \\frac{27}{7} \\ ; \\ -\\sqrt{\\frac{9}{4}} \\ ; \\ 6 \\ ; \\ 2\\pi \\ ; \\ \\sqrt{51} \\)","html":"\\( -\\sqrt{8} \\ ; \\ \\sqrt{19}\\ ; \\ \\text{0,45} \\ ; \\ \\text{0,}\\overline{45} ; \\ \\frac{27}{7} \\ ; \\ -\\sqrt{\\frac{9}{4}} \\ ; \\ 6 \\ ; \\ 2\\pi \\ ; \\ \\sqrt{51} \\)"}},"correct":false},{"id":"604f4bb8f6a894001fd57ba8","createdAt":"2021-03-15T11:57:44.957Z","updatedAt":"2021-03-15T11:57:44.957Z","deleted":false,"problemId":"6009648539384c001eed984d","solution":{"af":{"html":"% Solution Not Set","latex":"% Solution Not Set"},"en":{"html":"% Solution Not Set","latex":"% Solution Not Set"}},"correct":false}],"solutionImages":[],"images":[],"videos":[{"id":"5f8d975cdf26d44466082de2","createdAt":"2020-10-19T13:40:44.828Z","updatedAt":"2020-10-19T13:40:44.828Z","deleted":false,"name":"MathU Video 3","mimetype":"video/mp4","path":"https://storage.googleapis.com/mathu-content-dev-bucket/images/01yuKrIyjwM2O2qbqC8o.mp4","filename":"01yuKrIyjwM2O2qbqC8o.mp4","checksum":"f5c682b686132377e146ec0bca10bfb2"},{"id":"5f8d978bdf26d44466082eaf","createdAt":"2020-10-19T13:41:31.756Z","updatedAt":"2020-10-19T13:41:31.756Z","deleted":false,"name":"MathU Video 208","mimetype":"video/mp4","path":"https://storage.googleapis.com/mathu-content-dev-bucket/images/2PcIJ0FM754mrij415LH.mp4","filename":"2PcIJ0FM754mrij415LH.mp4","checksum":"6376bffe8a5f50d762614897610b47ca"},{"id":"5f8d97f9df26d44466083079","createdAt":"2020-10-19T13:43:21.477Z","updatedAt":"2020-10-19T13:43:21.477Z","deleted":false,"name":"MathU Video 666","mimetype":"video/mp4","path":"https://storage.googleapis.com/mathu-content-dev-bucket/images/7ewQQ89rERLGR5tysvpK.mp4","filename":"7ewQQ89rERLGR5tysvpK.mp4","checksum":"f58fc2515fb54eaf45d1db2bb7ff1a4f"},{"id":"5f8d981adf26d444660830fe","createdAt":"2020-10-19T13:43:54.278Z","updatedAt":"2020-10-19T13:43:54.278Z","deleted":false,"name":"MathU Video 799","mimetype":"video/mp4","path":"https://storage.googleapis.com/mathu-content-dev-bucket/images/9TvBWfMA5uxKzrRx4lxv.mp4","filename":"9TvBWfMA5uxKzrRx4lxv.mp4","checksum":"ce2f3f7024815420886bbf2d188a6b36"},{"id":"5f8d9938df26d44466083581","createdAt":"2020-10-19T13:48:40.326Z","updatedAt":"2020-10-19T13:48:40.326Z","deleted":false,"name":"MathU Video 1954","mimetype":"video/mp4","path":"https://storage.googleapis.com/mathu-content-dev-bucket/images/N9fEC3sZfFUbxl1ZBUlc.mp4","filename":"N9fEC3sZfFUbxl1ZBUlc.mp4","checksum":"b443c1e1a50879bb5d423dbc64dc75e9"},{"id":"5f8d993edf26d44466083598","createdAt":"2020-10-19T13:48:46.131Z","updatedAt":"2020-10-19T13:48:46.131Z","deleted":false,"name":"MathU Video 1977","mimetype":"video/mp4","path":"https://storage.googleapis.com/mathu-content-dev-bucket/images/NV7CHo6SOFV03o59YRiD.mp4","filename":"NV7CHo6SOFV03o59YRiD.mp4","checksum":"ca33b8e58895d13c6759e01ddaea6050"},{"id":"5f8d995adf26d44466083613","createdAt":"2020-10-19T13:49:14.266Z","updatedAt":"2020-10-19T13:49:14.266Z","deleted":false,"name":"MathU Video 2100","mimetype":"video/mp4","path":"https://storage.googleapis.com/mathu-content-dev-bucket/images/OruqdcyeCbS57DpVWZP9.mp4","filename":"OruqdcyeCbS57DpVWZP9.mp4","checksum":"70ba29be8c41cc275c1e0f51226ac46d"},{"id":"5f8d99c9df26d444660837e2","createdAt":"2020-10-19T13:51:05.394Z","updatedAt":"2020-10-19T13:51:05.394Z","deleted":false,"name":"MathU Video 2563","mimetype":"video/mp4","path":"https://storage.googleapis.com/mathu-content-dev-bucket/images/UXEAhgxmZMMBrOfltwkT.mp4","filename":"UXEAhgxmZMMBrOfltwkT.mp4","checksum":"45e39a95a2eacdf39309770c01381cb0"},{"id":"5f8d99e0df26d44466083841","createdAt":"2020-10-19T13:51:28.611Z","updatedAt":"2020-10-19T13:51:28.611Z","deleted":false,"name":"MathU Video 2658","mimetype":"video/mp4","path":"https://storage.googleapis.com/mathu-content-dev-bucket/images/VRCkGDzae3yosh9sZFuA.mp4","filename":"VRCkGDzae3yosh9sZFuA.mp4","checksum":"4aefa9ed191aec6e16d6cd14e3b73d31"},{"id":"5f8d9a0ddf26d444660838ee","createdAt":"2020-10-19T13:52:13.202Z","updatedAt":"2020-10-19T13:52:13.202Z","deleted":false,"name":"MathU Video 2831","mimetype":"video/mp4","path":"https://storage.googleapis.com/mathu-content-dev-bucket/images/XZaQe7lKhrOAtHpdzHck.mp4","filename":"XZaQe7lKhrOAtHpdzHck.mp4","checksum":"600d3feb1241f40e62a54dc1afbffca1"},{"id":"5f8d9a1ddf26d4446608392f","createdAt":"2020-10-19T13:52:29.553Z","updatedAt":"2020-10-19T13:52:29.553Z","deleted":false,"name":"MathU Video 2896","mimetype":"video/mp4","path":"https://storage.googleapis.com/mathu-content-dev-bucket/images/YKQRjIgKsADLUIfMWfou.mp4","filename":"YKQRjIgKsADLUIfMWfou.mp4","checksum":"20c91ee0f8646c1d21368a13077ba7c1"},{"id":"5f8d9aabdf26d44466083b85","createdAt":"2020-10-19T13:54:51.449Z","updatedAt":"2020-10-19T13:54:51.449Z","deleted":false,"name":"MathU Video 3494","mimetype":"video/mp4","path":"https://storage.googleapis.com/mathu-content-dev-bucket/images/fFQsdXDTKYZ6NnQKKpRn.mp4","filename":"fFQsdXDTKYZ6NnQKKpRn.mp4","checksum":"314699cdaa12b3dab5a12d447116f656"},{"id":"5f8d9abbdf26d44466083bc6","createdAt":"2020-10-19T13:55:07.725Z","updatedAt":"2020-10-19T13:55:07.725Z","deleted":false,"name":"MathU Video 3559","mimetype":"video/mp4","path":"https://storage.googleapis.com/mathu-content-dev-bucket/images/g5VVBhzH8XPhfDXTnbFh.mp4","filename":"g5VVBhzH8XPhfDXTnbFh.mp4","checksum":"6707592acdd6d618d8376eab6a9b439d"},{"id":"5f8d9b17df26d44466083d40","createdAt":"2020-10-19T13:56:39.045Z","updatedAt":"2020-10-19T13:56:39.045Z","deleted":false,"name":"MathU Video 3937","mimetype":"video/mp4","path":"https://storage.googleapis.com/mathu-content-dev-bucket/images/kqIqzqwjCCh6iMWYD0QQ.mp4","filename":"kqIqzqwjCCh6iMWYD0QQ.mp4","checksum":"273dae39ec943b30baaac22eae73e29c"},{"id":"5f8d9b7fdf26d44466083edd","createdAt":"2020-10-19T13:58:23.637Z","updatedAt":"2020-10-19T13:58:23.637Z","deleted":false,"name":"MathU Video 4350","mimetype":"video/mp4","path":"https://storage.googleapis.com/mathu-content-dev-bucket/images/pTUwJ1aanGOXT4VsW01G.mp4","filename":"pTUwJ1aanGOXT4VsW01G.mp4","checksum":"3515552e0c82aafb3f9ccdcc6d396ed4"}]}